sqlalchemy_data_model_visualizer.py
sqlalchemy_data_model_visualizer-0.1.3.dist-info/LICENSE
sqlalchemy_data_model_visualizer-0.1.3.dist-info/METADATA
sqlalchemy_data_model_visualizer-0.1.3.dist-info/WHEEL
sqlalchemy_data_model_visualizer-0.1.3.dist-info/top_level.txt
sqlalchemy_data_model_visualizer-0.1.3.dist-info/RECORD
