Metadata-Version: 2.1
Name: sqlalchemy_data_model_visualizer
Version: 0.1.3
Summary: A tool to visualize SQLAlchemy data models with Graphviz.
Home-page: https://github.com/Dicklesworthstone/sqlalchemy_data_model_visualizer
Author: Jeffrey Emanuel
Author-email: jeff@pastel.network
License: MIT
Keywords: sqlalchemy visualization graphviz data-model
Classifier: Development Status :: 3 - Alpha
Classifier: Intended Audience :: Developers
Classifier: License :: OSI Approved :: MIT License
Classifier: Programming Language :: Python :: 3
Classifier: Programming Language :: Python :: 3.8
Classifier: Programming Language :: Python :: 3.9
Classifier: Programming Language :: Python :: 3.10
Classifier: Programming Language :: Python :: 3.11
License-File: LICENSE
Requires-Dist: sqlalchemy
Requires-Dist: graphviz
Requires-Dist: lxml
